ticketguardian/__init__.py
ticketguardian/constants.py
ticketguardian/exceptions.py
ticketguardian/_project/__init__.py
ticketguardian/_project/_decorators.py
ticketguardian/_project/_validate/__init__.py
ticketguardian/_project/_validate/_address.py
ticketguardian/_project/_validate/_card.py
ticketguardian/_project/_validate/_customer.py
ticketguardian/_project/_validate/exceptions.py
ticketguardian/abstract/__init__.py
ticketguardian/abstract/api_resource.py
ticketguardian/abstract/delete_resource.py
ticketguardian/abstract/error_handling.py
ticketguardian/abstract/lazy_load_list.py
ticketguardian/abstract/list_resource.py
ticketguardian/abstract/patch_resource.py
ticketguardian/abstract/post_resource.py
ticketguardian/abstract/put_resource.py
ticketguardian/abstract/retrieve_resource.py
ticketguardian/abstract/sdk_exception.py
ticketguardian/abstract/tests/__init__.py
ticketguardian/abstract/tests/test_lazy_load_iterator.py
ticketguardian/abstract/tests/test_mixins.py
ticketguardian/abstract/tests/test_resourcelist.py
ticketguardian/affiliate/__init__.py
ticketguardian/affiliate/affiliate.py
ticketguardian/affiliate/tests/__init__.py
ticketguardian/affiliate/tests/test_affiliate_patch.py
ticketguardian/affiliate/tests/test_parent_scope.py
ticketguardian/auth/__init__.py
ticketguardian/auth/auth.py
ticketguardian/auth/tests/__init__.py
ticketguardian/auth/tests/test_auth.py
ticketguardian/client/__init__.py
ticketguardian/client/client.py
ticketguardian/client/tests/__init__.py
ticketguardian/client/tests/test_client.py
ticketguardian/client/tests/test_client_patch.py
ticketguardian/customer/__init__.py
ticketguardian/customer/customer.py
ticketguardian/customer/tests/__init__.py
ticketguardian/item/__init__.py
ticketguardian/item/item.py
ticketguardian/item/tests/__init__.py
ticketguardian/order/__init__.py
ticketguardian/order/exceptions.py
ticketguardian/order/order.py
ticketguardian/order/tests/__init__.py
ticketguardian/order/tests/test_add_items.py
ticketguardian_python-1.3.0.dist-info/LICENSE
ticketguardian_python-1.3.0.dist-info/METADATA
ticketguardian_python-1.3.0.dist-info/WHEEL
ticketguardian_python-1.3.0.dist-info/top_level.txt
ticketguardian_python-1.3.0.dist-info/RECORD
