Metadata-Version: 2.1
Name: ticketguardian-python
Version: 1.3.0
Summary: A python SDK for interacting with the TicketGuardian API
Home-page: https://github.com/TicketGuardian/ticketguardian-python
Author: TicketGuardian
Author-email: developers@protecht.io
License: UNKNOWN
Keywords: sdk,TicketGuardian,python
Platform: UNKNOWN
Requires-Dist: PyJWT (==1.5.3)
Requires-Dist: simplejson (==3.16.0)
Requires-Dist: requests[security]
